odoo/addons/product_matrix_show_color/README.rst
odoo/addons/product_matrix_show_color/__init__.py
odoo/addons/product_matrix_show_color/__manifest__.py
odoo/addons/product_matrix_show_color/i18n/es.po
odoo/addons/product_matrix_show_color/i18n/it.po
odoo/addons/product_matrix_show_color/i18n/product_matrix_show_color.pot
odoo/addons/product_matrix_show_color/models/__init__.py
odoo/addons/product_matrix_show_color/models/product_template.py
odoo/addons/product_matrix_show_color/readme/CONFIGURATION.rst
odoo/addons/product_matrix_show_color/readme/CONTRIBUTORS.rst
odoo/addons/product_matrix_show_color/readme/DESCRIPTION.rst
odoo/addons/product_matrix_show_color/readme/ROADMAP.rst
odoo/addons/product_matrix_show_color/readme/USAGE.rst
odoo/addons/product_matrix_show_color/static/description/icon.png
odoo/addons/product_matrix_show_color/static/description/index.html
odoo/addons/product_matrix_show_color/static/img/screenshot.png
odoo/addons/product_matrix_show_color/static/src/scss/product_matrix.scss
odoo/addons/product_matrix_show_color/static/src/xml/product_matrix.xml
odoo/addons/product_matrix_show_color/tests/__init__.py
odoo/addons/product_matrix_show_color/tests/test_product_template.py
odoo/addons/product_matrix_show_color/views/assets.xml
odoo14_addon_product_matrix_show_color-14.0.1.0.1.dev7.dist-info/METADATA
odoo14_addon_product_matrix_show_color-14.0.1.0.1.dev7.dist-info/WHEEL
odoo14_addon_product_matrix_show_color-14.0.1.0.1.dev7.dist-info/top_level.txt
odoo14_addon_product_matrix_show_color-14.0.1.0.1.dev7.dist-info/RECORD
